{"logged_at": "2026-04-26T14:38:11", "date": "2026-04-30", "name": "Brandon Woodruff", "team": "MIL", "opponent": "AZ", "home_away": "H", "predicted_pts": 12.7, "predicted_pts_raw": 12.7, "adj_total": 0, "adjustments": [], "base_pts": 12.3, "tier": "start", "status": "", "features": {"proj_era": 3.74, "proj_whip": 1.125, "proj_k9": 9.5, "opp_ops": "0.724", "opp_ops_raw": "0.717", "opp_rank": 8, "opp_k_pct": "21.1%", "park_factor": 1.02, "park": "MIL", "platoon": "", "opp_hand": "23% L", "vs_l_ops": ".617", "vs_r_ops": ".615", "tag": "UPSIDE", "trend": "", "recent_era": 3.77, "fb_velo": 92.5, "pitch_count": 6, "emerging": false, "opp_il_count": 0, "opp_il_returns_count": 1}}