{
  "BAL": {
    "left": 4,
    "right": 7,
    "switch": 2,
    "total": 13,
    "left_pct": 31,
    "right_pct": 54
  },
  "DET": {
    "left": 4,
    "right": 8,
    "switch": 1,
    "total": 13,
    "left_pct": 31,
    "right_pct": 62
  },
  "HOU": {
    "left": 4,
    "right": 9,
    "switch": 0,
    "total": 13,
    "left_pct": 31,
    "right_pct": 69
  },
  "LAA": {
    "left": 3,
    "right": 9,
    "switch": 1,
    "total": 13,
    "left_pct": 23,
    "right_pct": 69
  },
  "BOS": {
    "left": 5,
    "right": 8,
    "switch": 0,
    "total": 13,
    "left_pct": 38,
    "right_pct": 62
  },
  "CHC": {
    "left": 5,
    "right": 7,
    "switch": 1,
    "total": 13,
    "left_pct": 38,
    "right_pct": 54
  },
  "COL": {
    "left": 6,
    "right": 6,
    "switch": 1,
    "total": 13,
    "left_pct": 46,
    "right_pct": 46
  },
  "AZ": {
    "left": 3,
    "right": 6,
    "switch": 4,
    "total": 13,
    "left_pct": 23,
    "right_pct": 46
  },
  "CIN": {
    "left": 3,
    "right": 9,
    "switch": 1,
    "total": 13,
    "left_pct": 23,
    "right_pct": 69
  },
  "CLE": {
    "left": 6,
    "right": 3,
    "switch": 4,
    "total": 13,
    "left_pct": 46,
    "right_pct": 23
  },
  "KC": {
    "left": 5,
    "right": 7,
    "switch": 1,
    "total": 13,
    "left_pct": 38,
    "right_pct": 54
  },
  "NYM": {
    "left": 4,
    "right": 8,
    "switch": 1,
    "total": 13,
    "left_pct": 31,
    "right_pct": 62
  },
  "OAK": {
    "left": 5,
    "right": 8,
    "switch": 0,
    "total": 13,
    "left_pct": 38,
    "right_pct": 62
  },
  "WSH": {
    "left": 6,
    "right": 4,
    "switch": 3,
    "total": 13,
    "left_pct": 46,
    "right_pct": 31
  },
  "SD": {
    "left": 3,
    "right": 9,
    "switch": 1,
    "total": 13,
    "left_pct": 23,
    "right_pct": 69
  },
  "SF": {
    "left": 5,
    "right": 7,
    "switch": 1,
    "total": 13,
    "left_pct": 38,
    "right_pct": 54
  },
  "STL": {
    "left": 5,
    "right": 8,
    "switch": 0,
    "total": 13,
    "left_pct": 38,
    "right_pct": 62
  },
  "SEA": {
    "left": 5,
    "right": 6,
    "switch": 2,
    "total": 13,
    "left_pct": 38,
    "right_pct": 46
  },
  "LAD": {
    "left": 6,
    "right": 6,
    "switch": 1,
    "total": 13,
    "left_pct": 46,
    "right_pct": 46
  },
  "PIT": {
    "left": 4,
    "right": 7,
    "switch": 2,
    "total": 13,
    "left_pct": 31,
    "right_pct": 54
  },
  "TB": {
    "left": 6,
    "right": 6,
    "switch": 1,
    "total": 13,
    "left_pct": 46,
    "right_pct": 46
  },
  "TEX": {
    "left": 6,
    "right": 6,
    "switch": 1,
    "total": 13,
    "left_pct": 46,
    "right_pct": 46
  },
  "PHI": {
    "left": 6,
    "right": 6,
    "switch": 1,
    "total": 13,
    "left_pct": 46,
    "right_pct": 46
  },
  "MIN": {
    "left": 5,
    "right": 5,
    "switch": 3,
    "total": 13,
    "left_pct": 38,
    "right_pct": 38
  },
  "TOR": {
    "left": 4,
    "right": 7,
    "switch": 2,
    "total": 13,
    "left_pct": 31,
    "right_pct": 54
  },
  "MIA": {
    "left": 5,
    "right": 7,
    "switch": 1,
    "total": 13,
    "left_pct": 38,
    "right_pct": 54
  },
  "NYY": {
    "left": 7,
    "right": 6,
    "switch": 0,
    "total": 13,
    "left_pct": 54,
    "right_pct": 46
  },
  "CWS": {
    "left": 6,
    "right": 6,
    "switch": 1,
    "total": 13,
    "left_pct": 46,
    "right_pct": 46
  },
  "ATL": {
    "left": 5,
    "right": 6,
    "switch": 2,
    "total": 13,
    "left_pct": 38,
    "right_pct": 46
  },
  "MIL": {
    "left": 6,
    "right": 4,
    "switch": 3,
    "total": 13,
    "left_pct": 46,
    "right_pct": 31
  }
}